README.md
setup.py
calculos/__init__.py
calculos/classCalculo.py
calculos.egg-info/PKG-INFO
calculos.egg-info/SOURCES.txt
calculos.egg-info/dependency_links.txt
calculos.egg-info/not-zip-safe
calculos.egg-info/requires.txt
calculos.egg-info/top_level.txt