Metadata-Version: 2.1
Name: calculos
Version: 1.0
Summary: Módulo de calculos simples para calculadora em Python
Home-page: https://github.com/Jeferson777
Author: Jeferson Soaris
Author-email: g7harmonic@outlook.com
License: GNU GENERAL PUBLIC LICENSE
Platform: UNKNOWN
Classifier: Development Status :: 2 - Pre-Alpha
Classifier: Environment :: Console
Classifier: Intended Audience :: Developers
Classifier: License :: OSI Approved :: GNU Affero General Public License v3 or later (AGPLv3+)
Classifier: Operating System :: OS Independent
Classifier: Programming Language :: Python
Classifier: Programming Language :: Python :: 3.8
Classifier: Programming Language :: Python :: 3.9
Classifier: Framework :: Pytest
